{
  "slug": "2026-07-12-storage-design-chip-silicon-wafer-price-hike",
  "title": "北京君正确认DRAM逐季提价，半导体硅片指数年内涨幅近翻倍",
  "date": "2026-07-01",
  "reported": "2026-07-12",
  "sector": "存储芯片设计厂商及半导体硅片",
  "change": "↑↑",
  "level": "强势",
  "what": "存储芯片设计厂商北京君正(300223)7月1日在机构调研中确认：DRAM产品一季度国内客户已开始调价、二季度国内外客户持续涨价、三季度价格将继续上调，四季度供应仍紧张存在进一步调价可能性，公司存储芯片持续涨价带动毛利率逐季环比提升。同期受益于全球硅片厂商接连开启涨价周期及AI算力拉动的需求重构，半导体硅片指数截至7月12日年内涨幅逼近翻倍，立昂微(605358)、沪硅产业(688126)等12英寸硅片产销量大幅增长，立昂微预计2026年上半年归母净利润8500万元，同比扭亏为盈。",
  "leaders": "北京君正(300223)·立昂微(605358)·沪硅产业(688126)·兆易创新(603986)",
  "risk": "存储设计厂商的提价能力依赖上游晶圆代工产能分配及自身议价权，与三星/美光等IDM原厂的官方调价函存在传导时滞；硅片指数年内已翻倍，估值消化及新增产能释放节奏需持续跟踪。",
  "summary": "北京君正7月初确认DRAM产品价格逐季持续上调、四季度仍有调价空间；同期半导体硅片指数年内涨幅逼近翻倍，立昂微、沪硅产业等12英寸硅片厂商量价齐升。",
  "source_name": "新浪网",
  "source_url": "https://www.sina.cn/news/detail/5316330627801673.html"
}
